tarvis/indicators/webapi/__init__.py
tarvis_indicators_webapi-0.9.11.dist-info/LICENSE.txt
tarvis_indicators_webapi-0.9.11.dist-info/METADATA
tarvis_indicators_webapi-0.9.11.dist-info/WHEEL
tarvis_indicators_webapi-0.9.11.dist-info/top_level.txt
tarvis_indicators_webapi-0.9.11.dist-info/RECORD
