Metadata-Version: 2.1
Name: tarvis-indicators-webapi
Version: 0.9.11
Summary: Tarvis Web API Indicators Library
Home-page: https://tarvislabs.com/
Author: Tarvis Labs
Author-email: python@tarvislabs.com
License: UNKNOWN
Platform: UNKNOWN
Requires-Python: >=3.10
License-File: LICENSE.txt
Requires-Dist: requests (==2.28.1)
Requires-Dist: tarvis-common (==0.9.11)
